jizhi/__init__.py
jizhi/client.py
jizhi/exception.py
jizhi/model.py
jizhi-0.1.1.dist-info/DESCRIPTION.rst
jizhi-0.1.1.dist-info/METADATA
jizhi-0.1.1.dist-info/metadata.json
jizhi-0.1.1.dist-info/RECORD
jizhi-0.1.1.dist-info/top_level.txt
jizhi-0.1.1.dist-info/WHEEL
