Metadata-Version: 2.0
Name: jizhi
Version: 0.1.1
Summary: jizhi api SDK
Home-page: http://www.crowdsdom.com
Author: Jizhi Inc.
Author-email: UNKNOWN
License: UNKNOWN
Keywords: jizhi oauth 2.0 client
Platform: UNKNOWN
Classifier: Programming Language :: Python :: 2
Classifier: Programming Language :: Python :: 2.6
Classifier: Programming Language :: Python :: 2.7
Classifier: Programming Language :: Python :: 3
Classifier: Programming Language :: Python :: 3.3
Classifier: Programming Language :: Python :: 3.4
Classifier: Topic :: Internet :: WWW/HTTP
Requires-Dist: requests (>=2.7.0)
